<?xml version="1.0" encoding="UTF-8"?>
<!DOCTYPE plist PUBLIC "-//Apple Computer//DTD PLIST 1.0//EN" "http://www.apple.com/DTDs/PropertyList-1.0.dtd">
<plist version="1.0">
    <dict>
        <key>frames</key>
        <dict>
            <key>BetHolder.png</key>
            <dict>
                <key>frame</key>
                <string>{{141,682},{248,35}}</string>
                <key>offset</key>
                <string>{0,0}</string>
                <key>rotated</key>
                <false/>
                <key>sourceColorRect</key>
                <string>{{0,0},{248,35}}</string>
                <key>sourceSize</key>
                <string>{248,35}</string>
            </dict>
            <key>Buttons/AddChips_Button.png</key>
            <dict>
                <key>frame</key>
                <string>{{959,552},{41,60}}</string>
                <key>offset</key>
                <string>{0,0}</string>
                <key>rotated</key>
                <false/>
                <key>sourceColorRect</key>
                <string>{{0,0},{41,60}}</string>
                <key>sourceSize</key>
                <string>{41,60}</string>
            </dict>
            <key>Buttons/AddChips_Button_Pressed.png</key>
            <dict>
                <key>frame</key>
                <string>{{959,492},{41,60}}</string>
                <key>offset</key>
                <string>{0,0}</string>
                <key>rotated</key>
                <false/>
                <key>sourceColorRect</key>
                <string>{{0,0},{41,60}}</string>
                <key>sourceSize</key>
                <string>{41,60}</string>
            </dict>
            <key>Buttons/Back_Button.png</key>
            <dict>
                <key>frame</key>
                <string>{{609,451},{141,81}}</string>
                <key>offset</key>
                <string>{0,0}</string>
                <key>rotated</key>
                <false/>
                <key>sourceColorRect</key>
                <string>{{0,0},{141,81}}</string>
                <key>sourceSize</key>
                <string>{141,81}</string>
            </dict>
            <key>Buttons/Back_Button_Disabled.png</key>
            <dict>
                <key>frame</key>
                <string>{{750,413},{141,81}}</string>
                <key>offset</key>
                <string>{0,0}</string>
                <key>rotated</key>
                <false/>
                <key>sourceColorRect</key>
                <string>{{0,0},{141,81}}</string>
                <key>sourceSize</key>
                <string>{141,81}</string>
            </dict>
            <key>Buttons/Back_Button_Pressed.png</key>
            <dict>
                <key>frame</key>
                <string>{{609,370},{141,81}}</string>
                <key>offset</key>
                <string>{0,0}</string>
                <key>rotated</key>
                <false/>
                <key>sourceColorRect</key>
                <string>{{0,0},{141,81}}</string>
                <key>sourceSize</key>
                <string>{141,81}</string>
            </dict>
            <key>Buttons/Button_MusicOff.png</key>
            <dict>
                <key>frame</key>
                <string>{{885,562},{68,70}}</string>
                <key>offset</key>
                <string>{0,0}</string>
                <key>rotated</key>
                <false/>
                <key>sourceColorRect</key>
                <string>{{0,0},{68,70}}</string>
                <key>sourceSize</key>
                <string>{68,70}</string>
            </dict>
            <key>Buttons/Button_MusicOn.png</key>
            <dict>
                <key>frame</key>
                <string>{{891,492},{68,70}}</string>
                <key>offset</key>
                <string>{0,0}</string>
                <key>rotated</key>
                <false/>
                <key>sourceColorRect</key>
                <string>{{0,0},{68,70}}</string>
                <key>sourceSize</key>
                <string>{68,70}</string>
            </dict>
            <key>Buttons/Button_SoundOff.png</key>
            <dict>
                <key>frame</key>
                <string>{{175,330},{68,70}}</string>
                <key>offset</key>
                <string>{0,0}</string>
                <key>rotated</key>
                <false/>
                <key>sourceColorRect</key>
                <string>{{0,0},{68,70}}</string>
                <key>sourceSize</key>
                <string>{68,70}</string>
            </dict>
            <key>Buttons/Button_SoundOn.png</key>
            <dict>
                <key>frame</key>
                <string>{{175,260},{68,70}}</string>
                <key>offset</key>
                <string>{0,0}</string>
                <key>rotated</key>
                <false/>
                <key>sourceColorRect</key>
                <string>{{0,0},{68,70}}</string>
                <key>sourceSize</key>
                <string>{68,70}</string>
            </dict>
            <key>Buttons/ClaimBonus_Button.png</key>
            <dict>
                <key>frame</key>
                <string>{{570,749},{222,38}}</string>
                <key>offset</key>
                <string>{0,0}</string>
                <key>rotated</key>
                <false/>
                <key>sourceColorRect</key>
                <string>{{0,0},{222,38}}</string>
                <key>sourceSize</key>
                <string>{222,38}</string>
            </dict>
            <key>Buttons/ClaimBonus_Button_Disabled.png</key>
            <dict>
                <key>frame</key>
                <string>{{348,732},{222,38}}</string>
                <key>offset</key>
                <string>{0,0}</string>
                <key>rotated</key>
                <false/>
                <key>sourceColorRect</key>
                <string>{{0,0},{222,38}}</string>
                <key>sourceSize</key>
                <string>{222,38}</string>
            </dict>
            <key>Buttons/ClaimBonus_Button_Pressed.png</key>
            <dict>
                <key>frame</key>
                <string>{{573,711},{222,38}}</string>
                <key>offset</key>
                <string>{0,0}</string>
                <key>rotated</key>
                <false/>
                <key>sourceColorRect</key>
                <string>{{0,0},{222,38}}</string>
                <key>sourceSize</key>
                <string>{222,38}</string>
            </dict>
            <key>Buttons/Clear_Button.png</key>
            <dict>
                <key>frame</key>
                <string>{{769,332},{141,81}}</string>
                <key>offset</key>
                <string>{0,0}</string>
                <key>rotated</key>
                <false/>
                <key>sourceColorRect</key>
                <string>{{0,0},{141,81}}</string>
                <key>sourceSize</key>
                <string>{141,81}</string>
            </dict>
            <key>Buttons/Clear_Button_Disabled.png</key>
            <dict>
                <key>frame</key>
                <string>{{769,251},{141,81}}</string>
                <key>offset</key>
                <string>{0,0}</string>
                <key>rotated</key>
                <false/>
                <key>sourceColorRect</key>
                <string>{{0,0},{141,81}}</string>
                <key>sourceSize</key>
                <string>{141,81}</string>
            </dict>
            <key>Buttons/Clear_Button_Pressed.png</key>
            <dict>
                <key>frame</key>
                <string>{{769,170},{141,81}}</string>
                <key>offset</key>
                <string>{0,0}</string>
                <key>rotated</key>
                <false/>
                <key>sourceColorRect</key>
                <string>{{0,0},{141,81}}</string>
                <key>sourceSize</key>
                <string>{141,81}</string>
            </dict>
            <key>Buttons/Deal_Button.png</key>
            <dict>
                <key>frame</key>
                <string>{{0,175},{244,85}}</string>
                <key>offset</key>
                <string>{0,0}</string>
                <key>rotated</key>
                <false/>
                <key>sourceColorRect</key>
                <string>{{0,0},{244,85}}</string>
                <key>sourceSize</key>
                <string>{244,85}</string>
            </dict>
            <key>Buttons/Deal_Button_Disabled.png</key>
            <dict>
                <key>frame</key>
                <string>{{0,90},{244,85}}</string>
                <key>offset</key>
                <string>{0,0}</string>
                <key>rotated</key>
                <false/>
                <key>sourceColorRect</key>
                <string>{{0,0},{244,85}}</string>
                <key>sourceSize</key>
                <string>{244,85}</string>
            </dict>
            <key>Buttons/Deal_Button_Pressed.png</key>
            <dict>
                <key>frame</key>
                <string>{{682,85},{244,85}}</string>
                <key>offset</key>
                <string>{0,0}</string>
                <key>rotated</key>
                <false/>
                <key>sourceColorRect</key>
                <string>{{0,0},{244,85}}</string>
                <key>sourceSize</key>
                <string>{244,85}</string>
            </dict>
            <key>Buttons/Double_Button.png</key>
            <dict>
                <key>frame</key>
                <string>{{594,270},{175,100}}</string>
                <key>offset</key>
                <string>{0,0}</string>
                <key>rotated</key>
                <false/>
                <key>sourceColorRect</key>
                <string>{{0,0},{175,100}}</string>
                <key>sourceSize</key>
                <string>{175,100}</string>
            </dict>
            <key>Buttons/Double_Button_Disabled.png</key>
            <dict>
                <key>frame</key>
                <string>{{0,360},{175,100}}</string>
                <key>offset</key>
                <string>{0,0}</string>
                <key>rotated</key>
                <false/>
                <key>sourceColorRect</key>
                <string>{{0,0},{175,100}}</string>
                <key>sourceSize</key>
                <string>{175,100}</string>
            </dict>
            <key>Buttons/Double_Button_Pressed.png</key>
            <dict>
                <key>frame</key>
                <string>{{243,290},{175,100}}</string>
                <key>offset</key>
                <string>{0,0}</string>
                <key>rotated</key>
                <false/>
                <key>sourceColorRect</key>
                <string>{{0,0},{175,100}}</string>
                <key>sourceSize</key>
                <string>{175,100}</string>
            </dict>
            <key>Buttons/Hit_Button.png</key>
            <dict>
                <key>frame</key>
                <string>{{799,710},{191,85}}</string>
                <key>offset</key>
                <string>{0,0}</string>
                <key>rotated</key>
                <false/>
                <key>sourceColorRect</key>
                <string>{{0,0},{191,85}}</string>
                <key>sourceSize</key>
                <string>{191,85}</string>
            </dict>
            <key>Buttons/Hit_Button_Disabled.png</key>
            <dict>
                <key>frame</key>
                <string>{{326,540},{191,85}}</string>
                <key>offset</key>
                <string>{0,0}</string>
                <key>rotated</key>
                <false/>
                <key>sourceColorRect</key>
                <string>{{0,0},{191,85}}</string>
                <key>sourceSize</key>
                <string>{191,85}</string>
            </dict>
            <key>Buttons/Hit_Button_Pressed.png</key>
            <dict>
                <key>frame</key>
                <string>{{0,545},{191,85}}</string>
                <key>offset</key>
                <string>{0,0}</string>
                <key>rotated</key>
                <false/>
                <key>sourceColorRect</key>
                <string>{{0,0},{191,85}}</string>
                <key>sourceSize</key>
                <string>{191,85}</string>
            </dict>
            <key>Buttons/No_Button.png</key>
            <dict>
                <key>frame</key>
                <string>{{191,468},{135,78}}</string>
                <key>offset</key>
                <string>{0,0}</string>
                <key>rotated</key>
                <false/>
                <key>sourceColorRect</key>
                <string>{{0,0},{135,78}}</string>
                <key>sourceSize</key>
                <string>{135,78}</string>
            </dict>
            <key>Buttons/No_Button_Disabled.png</key>
            <dict>
                <key>frame</key>
                <string>{{839,632},{135,78}}</string>
                <key>offset</key>
                <string>{0,0}</string>
                <key>rotated</key>
                <false/>
                <key>sourceColorRect</key>
                <string>{{0,0},{135,78}}</string>
                <key>sourceSize</key>
                <string>{135,78}</string>
            </dict>
            <key>Buttons/No_Button_Pressed.png</key>
            <dict>
                <key>frame</key>
                <string>{{704,572},{135,78}}</string>
                <key>offset</key>
                <string>{0,0}</string>
                <key>rotated</key>
                <false/>
                <key>sourceColorRect</key>
                <string>{{0,0},{135,78}}</string>
                <key>sourceSize</key>
                <string>{135,78}</string>
            </dict>
            <key>Buttons/Rebet_Button.png</key>
            <dict>
                <key>frame</key>
                <string>{{438,85},{244,85}}</string>
                <key>offset</key>
                <string>{0,0}</string>
                <key>rotated</key>
                <false/>
                <key>sourceColorRect</key>
                <string>{{0,0},{244,85}}</string>
                <key>sourceSize</key>
                <string>{244,85}</string>
            </dict>
            <key>Buttons/Rebet_Button_Disabled.png</key>
            <dict>
                <key>frame</key>
                <string>{{682,0},{244,85}}</string>
                <key>offset</key>
                <string>{0,0}</string>
                <key>rotated</key>
                <false/>
                <key>sourceColorRect</key>
                <string>{{0,0},{244,85}}</string>
                <key>sourceSize</key>
                <string>{244,85}</string>
            </dict>
            <key>Buttons/Rebet_Button_Pressed.png</key>
            <dict>
                <key>frame</key>
                <string>{{438,0},{244,85}}</string>
                <key>offset</key>
                <string>{0,0}</string>
                <key>rotated</key>
                <false/>
                <key>sourceColorRect</key>
                <string>{{0,0},{244,85}}</string>
                <key>sourceSize</key>
                <string>{244,85}</string>
            </dict>
            <key>Buttons/RemoveAds_Button.png</key>
            <dict>
                <key>frame</key>
                <string>{{432,671},{141,61}}</string>
                <key>offset</key>
                <string>{0,0}</string>
                <key>rotated</key>
                <false/>
                <key>sourceColorRect</key>
                <string>{{0,0},{141,61}}</string>
                <key>sourceSize</key>
                <string>{141,61}</string>
            </dict>
            <key>Buttons/RemoveAds_Button_Pressed.png</key>
            <dict>
                <key>frame</key>
                <string>{{0,630},{141,61}}</string>
                <key>offset</key>
                <string>{0,0}</string>
                <key>rotated</key>
                <false/>
                <key>sourceColorRect</key>
                <string>{{0,0},{141,61}}</string>
                <key>sourceSize</key>
                <string>{141,61}</string>
            </dict>
            <key>Buttons/RestorePurchase_Button.png</key>
            <dict>
                <key>frame</key>
                <string>{{658,650},{141,61}}</string>
                <key>offset</key>
                <string>{0,0}</string>
                <key>rotated</key>
                <false/>
                <key>sourceColorRect</key>
                <string>{{0,0},{141,61}}</string>
                <key>sourceSize</key>
                <string>{141,61}</string>
            </dict>
            <key>Buttons/RestorePurchase_Button_Pressed.png</key>
            <dict>
                <key>frame</key>
                <string>{{517,610},{141,61}}</string>
                <key>offset</key>
                <string>{0,0}</string>
                <key>rotated</key>
                <false/>
                <key>sourceColorRect</key>
                <string>{{0,0},{141,61}}</string>
                <key>sourceSize</key>
                <string>{141,61}</string>
            </dict>
            <key>Buttons/Split_Button.png</key>
            <dict>
                <key>frame</key>
                <string>{{419,270},{175,100}}</string>
                <key>offset</key>
                <string>{0,0}</string>
                <key>rotated</key>
                <false/>
                <key>sourceColorRect</key>
                <string>{{0,0},{175,100}}</string>
                <key>sourceSize</key>
                <string>{175,100}</string>
            </dict>
            <key>Buttons/Split_Button_Disabled.png</key>
            <dict>
                <key>frame</key>
                <string>{{594,170},{175,100}}</string>
                <key>offset</key>
                <string>{0,0}</string>
                <key>rotated</key>
                <false/>
                <key>sourceColorRect</key>
                <string>{{0,0},{175,100}}</string>
                <key>sourceSize</key>
                <string>{175,100}</string>
            </dict>
            <key>Buttons/Split_Button_Pressed.png</key>
            <dict>
                <key>frame</key>
                <string>{{0,260},{175,100}}</string>
                <key>offset</key>
                <string>{0,0}</string>
                <key>rotated</key>
                <false/>
                <key>sourceColorRect</key>
                <string>{{0,0},{175,100}}</string>
                <key>sourceSize</key>
                <string>{175,100}</string>
            </dict>
            <key>Buttons/Stand_Button.png</key>
            <dict>
                <key>frame</key>
                <string>{{0,460},{191,85}}</string>
                <key>offset</key>
                <string>{0,0}</string>
                <key>rotated</key>
                <false/>
                <key>sourceColorRect</key>
                <string>{{0,0},{191,85}}</string>
                <key>sourceSize</key>
                <string>{191,85}</string>
            </dict>
            <key>Buttons/Stand_Button_Disabled.png</key>
            <dict>
                <key>frame</key>
                <string>{{378,455},{191,85}}</string>
                <key>offset</key>
                <string>{0,0}</string>
                <key>rotated</key>
                <false/>
                <key>sourceColorRect</key>
                <string>{{0,0},{191,85}}</string>
                <key>sourceSize</key>
                <string>{191,85}</string>
            </dict>
            <key>Buttons/Stand_Button_Pressed.png</key>
            <dict>
                <key>frame</key>
                <string>{{418,370},{191,85}}</string>
                <key>offset</key>
                <string>{0,0}</string>
                <key>rotated</key>
                <false/>
                <key>sourceColorRect</key>
                <string>{{0,0},{191,85}}</string>
                <key>sourceSize</key>
                <string>{191,85}</string>
            </dict>
            <key>Buttons/Surrender_Button.png</key>
            <dict>
                <key>frame</key>
                <string>{{244,190},{175,100}}</string>
                <key>offset</key>
                <string>{0,0}</string>
                <key>rotated</key>
                <false/>
                <key>sourceColorRect</key>
                <string>{{0,0},{175,100}}</string>
                <key>sourceSize</key>
                <string>{175,100}</string>
            </dict>
            <key>Buttons/Surrender_Button_Disabled.png</key>
            <dict>
                <key>frame</key>
                <string>{{419,170},{175,100}}</string>
                <key>offset</key>
                <string>{0,0}</string>
                <key>rotated</key>
                <false/>
                <key>sourceColorRect</key>
                <string>{{0,0},{175,100}}</string>
                <key>sourceSize</key>
                <string>{175,100}</string>
            </dict>
            <key>Buttons/Surrender_Button_Pressed.png</key>
            <dict>
                <key>frame</key>
                <string>{{244,90},{175,100}}</string>
                <key>offset</key>
                <string>{0,0}</string>
                <key>rotated</key>
                <false/>
                <key>sourceColorRect</key>
                <string>{{0,0},{175,100}}</string>
                <key>sourceSize</key>
                <string>{175,100}</string>
            </dict>
            <key>Buttons/Yes_Button.png</key>
            <dict>
                <key>frame</key>
                <string>{{569,532},{135,78}}</string>
                <key>offset</key>
                <string>{0,0}</string>
                <key>rotated</key>
                <false/>
                <key>sourceColorRect</key>
                <string>{{0,0},{135,78}}</string>
                <key>sourceSize</key>
                <string>{135,78}</string>
            </dict>
            <key>Buttons/Yes_Button_Disabled.png</key>
            <dict>
                <key>frame</key>
                <string>{{243,390},{135,78}}</string>
                <key>offset</key>
                <string>{0,0}</string>
                <key>rotated</key>
                <false/>
                <key>sourceColorRect</key>
                <string>{{0,0},{135,78}}</string>
                <key>sourceSize</key>
                <string>{135,78}</string>
            </dict>
            <key>Buttons/Yes_Button_Pressed.png</key>
            <dict>
                <key>frame</key>
                <string>{{750,494},{135,78}}</string>
                <key>offset</key>
                <string>{0,0}</string>
                <key>rotated</key>
                <false/>
                <key>sourceColorRect</key>
                <string>{{0,0},{135,78}}</string>
                <key>sourceSize</key>
                <string>{135,78}</string>
            </dict>
            <key>ChipBalanceHolder.png</key>
            <dict>
                <key>frame</key>
                <string>{{0,0},{438,90}}</string>
                <key>offset</key>
                <string>{0,0}</string>
                <key>rotated</key>
                <false/>
                <key>sourceColorRect</key>
                <string>{{0,0},{438,90}}</string>
                <key>sourceSize</key>
                <string>{438,90}</string>
            </dict>
            <key>DG_Chip/DG_Chip_1.png</key>
            <dict>
                <key>frame</key>
                <string>{{910,410},{82,82}}</string>
                <key>offset</key>
                <string>{0,0}</string>
                <key>rotated</key>
                <false/>
                <key>sourceColorRect</key>
                <string>{{0,0},{82,82}}</string>
                <key>sourceSize</key>
                <string>{82,82}</string>
            </dict>
            <key>DG_Chip/DG_Chip_2.png</key>
            <dict>
                <key>frame</key>
                <string>{{910,328},{82,82}}</string>
                <key>offset</key>
                <string>{0,0}</string>
                <key>rotated</key>
                <false/>
                <key>sourceColorRect</key>
                <string>{{0,0},{82,82}}</string>
                <key>sourceSize</key>
                <string>{82,82}</string>
            </dict>
            <key>DG_Chip/DG_Chip_3.png</key>
            <dict>
                <key>frame</key>
                <string>{{910,246},{82,82}}</string>
                <key>offset</key>
                <string>{0,0}</string>
                <key>rotated</key>
                <false/>
                <key>sourceColorRect</key>
                <string>{{0,0},{82,82}}</string>
                <key>sourceSize</key>
                <string>{82,82}</string>
            </dict>
            <key>DG_Chip/DG_Chip_4.png</key>
            <dict>
                <key>frame</key>
                <string>{{926,164},{82,82}}</string>
                <key>offset</key>
                <string>{0,0}</string>
                <key>rotated</key>
                <false/>
                <key>sourceColorRect</key>
                <string>{{0,0},{82,82}}</string>
                <key>sourceSize</key>
                <string>{82,82}</string>
            </dict>
            <key>DG_Chip/DG_Chip_5.png</key>
            <dict>
                <key>frame</key>
                <string>{{926,82},{82,82}}</string>
                <key>offset</key>
                <string>{0,0}</string>
                <key>rotated</key>
                <false/>
                <key>sourceColorRect</key>
                <string>{{0,0},{82,82}}</string>
                <key>sourceSize</key>
                <string>{82,82}</string>
            </dict>
            <key>DG_Chip/DG_Chip_6.png</key>
            <dict>
                <key>frame</key>
                <string>{{926,0},{82,82}}</string>
                <key>offset</key>
                <string>{0,0}</string>
                <key>rotated</key>
                <false/>
                <key>sourceColorRect</key>
                <string>{{0,0},{82,82}}</string>
                <key>sourceSize</key>
                <string>{82,82}</string>
            </dict>
            <key>NumberFont.png</key>
            <dict>
                <key>frame</key>
                <string>{{0,717},{348,42}}</string>
                <key>offset</key>
                <string>{0,0}</string>
                <key>rotated</key>
                <false/>
                <key>sourceColorRect</key>
                <string>{{0,0},{348,42}}</string>
                <key>sourceSize</key>
                <string>{348,42}</string>
            </dict>
            <key>NumberFont1.png</key>
            <dict>
                <key>frame</key>
                <string>{{324,787},{324,38}}</string>
                <key>offset</key>
                <string>{0,0}</string>
                <key>rotated</key>
                <false/>
                <key>sourceColorRect</key>
                <string>{{0,0},{324,38}}</string>
                <key>sourceSize</key>
                <string>{324,38}</string>
            </dict>
            <key>NumberFont2.png</key>
            <dict>
                <key>frame</key>
                <string>{{0,759},{324,38}}</string>
                <key>offset</key>
                <string>{0,0}</string>
                <key>rotated</key>
                <false/>
                <key>sourceColorRect</key>
                <string>{{0,0},{324,38}}</string>
                <key>sourceSize</key>
                <string>{324,38}</string>
            </dict>
            <key>TimerHolder.png</key>
            <dict>
                <key>frame</key>
                <string>{{191,625},{241,57}}</string>
                <key>offset</key>
                <string>{0,0}</string>
                <key>rotated</key>
                <false/>
                <key>sourceColorRect</key>
                <string>{{0,0},{241,57}}</string>
                <key>sourceSize</key>
                <string>{241,57}</string>
            </dict>
        </dict>
        <key>metadata</key>
        <dict>
            <key>format</key>
            <integer>2</integer>
            <key>realTextureFileName</key>
            <string>BJ_BottomBar.png</string>
            <key>size</key>
            <string>{1008,825}</string>
            <key>smartupdate</key>
            <string>$TexturePacker:SmartUpdate:450cb42fe71d378675073cde1f273114$</string>
            <key>textureFileName</key>
            <string>BJ_BottomBar.png</string>
        </dict>
    </dict>
</plist>
